dubidoc/__init__.py
dubidoc/client.py
dubidoc/enum.py
dubidoc/response.py
dubidoc/_modules/__init__.py
dubidoc/_modules/access_token.py
dubidoc/_modules/authentication.py
dubidoc/_modules/device.py
dubidoc/_modules/document.py
dubidoc/_modules/document_link.py
dubidoc/_modules/download.py
dubidoc/_modules/organization.py
dubidoc/_modules/organization_user.py
dubidoc/_modules/participant.py
dubidoc/_modules/storecode.py
dubidoc-0.2.0.dist-info/licenses/LICENSE
dubidoc-0.2.0.dist-info/METADATA
dubidoc-0.2.0.dist-info/WHEEL
dubidoc-0.2.0.dist-info/top_level.txt
dubidoc-0.2.0.dist-info/RECORD
